Workbook

Sheet Sheet1
A1: sr.no. | B1: publication_title | C1: issn | D1: eissn | E1: date_first_issue_online | F1: date_last_issue_online | G1: publisher_name | H1: publication_type | I1: title_url | J1: title_id | K1: coverage_depth | L1: coverage_notes | M1: subjectname | N1: provider_name | O1: collectionname | P1: id | Q1: scopusid | R1: asjc codes_y | S1: active or inactive_y | T1: coverage_y | U1: Subject Keywords | V1: Main Subject | W1: Supergroup
A2: 1 | B2: Science | C2: 0036-8075 | D2: 1095-9203 | E2: 1997 | G2: American Association for the Advancement of Science | H2: serial | I2: https://www.science.org/journal/science | M2: Multidisciplinary | N2: ONOS | O2: AAAS- Science | P2: 60710 | Q2: 23571 | R2: 1000 | S2: Active | T2: 1883-2026; 1880-1881 | U2: Multidisciplinary | V2: Multidisciplinary | W2: Multidisciplinary
A3: 2 | B3: ACM Computing Surveys | C3: 0360-0300 | D3: 1557-7341 | E3: 1969 | G3: Association for Computing Machinery | H3: serial | I3: https://dl.acm.org/loi/csur | M3: Condensed Matter Physics; Mechanics of Materials; General Materials Science; General Chemistry; Mechanical Engineering | N3: ONOS | O3: ACM Digital Library | P3: 20887 | Q3: 23038 | R3: 1700; 2614 | S3: Active | T3: 1969-2026 | U3: General Computer Science; Theoretical Computer Science | V3: Computer Science; Mathematics | W3: Physical Sciences
A4: 3 | B4: ACM Journal of Computer Documentation | C4: 1527-6805 | D4: 1557-9441 | E4: 2000 | F4: 2002 | G4: Association for Computing Machinery | H4: serial | I4: https://dl.acm.org/loi/jcd | M4: General Computer Science | N4: ONOS | O4: ACM Digital Library | P4: 20888 | R4: 1700 | U4: General Computer Science | V4: Computer Science | W4: Physical Sciences
A5: 4 | B5: ACM Journal on Emerging Technologies in Computing Systems | C5: 1550-4832 | D5: 1550-4840 | E5: 2005 | G5: Association for Computing Machinery | H5: serial | I5: https://dl.acm.org/loi/jetc | M5: Hardware and Architecture; Software; Electrical and Electronic Engineering | N5: ONOS | O5: ACM Digital Library | P5: 20889 | Q5: 4700152798 | R5: 2208; 1708; 1712 | S5: Active | T5: 2005-2026 | U5: Electrical and Electronic Engineering; Hardware and Architecture; Software | V5: Engineering; Computer Science | W5: Physical Sciences
A6: 5 | B6: Journal of Data and Information Quality | C6: 1936-1955 | D6: 1936-1963 | E6: 2009 | G6: Association for Computing Machinery | H6: serial | I6: https://dl.acm.org/loi/jdiq | M6: Information Systems; Information Systems and Management | N6: ONOS | O6: ACM Digital Library | P6: 20890 | Q6: 19700186884 | R6: 1802; 1710 | S6: Active | T6: 2009-2025 | U6: Information Systems and Management; Information Systems | V6: Decision Sciences; Computer Science | W6: Social Sciences; Physical Sciences
A7: 6 | B7: Journal of Experimental Algorithmics | C7: 1084-6654 | D7: 1084-6654 | E7: 1996 | G7: Association for Computing Machinery | H7: serial | I7: https://dl.acm.org/loi/jea | M7: Theoretical Computer Science | N7: ONOS | O7: ACM Digital Library | P7: 20891 | Q7: 12100155656 | R7: 2614 | S7: Inactive | T7: 1996-2023 | U7: Theoretical Computer Science | V7: Mathematics | W7: Physical Sciences
A8: 7 | B8: Journal of the ACM | C8: 0004-5411 | D8: 1557-735X | E8: 1954 | G8: Association for Computing Machinery | H8: serial | I8: https://dl.acm.org/loi/jacm | M8: Condensed Matter Physics; Mechanics of Materials; General Materials Science; General Chemistry; Mechanical Engineering | N8: ONOS | O8: ACM Digital Library | P8: 20892 | Q8: 23127 | R8: 1708; 1710; 2207; 1702; 1712 | S8: Active | T8: 1954-2026 | U8: Hardware and Architecture; Information Systems; Control and Systems Engineering; Artificial Intelligence; Software | V8: Computer Science; Engineering | W8: Physical Sciences
A9: 8 | B9: Journal on Computing and Cultural Heritage | C9: 1556-4673 | D9: 1556-4711 | E9: 2008 | G9: Association for Computing Machinery | H9: serial | I9: https://dl.acm.org/loi/jocch | M9: Information Systems; Computer Science Applications; Conservation; Computer Graphics and Computer-Aided Design | N9: ONOS | O9: ACM Digital Library | P9: 20893 | Q9: 19400157014 | R9: 1704; 1706; 1710; 1206 | S9: Active | T9: 2008-2026 | U9: Computer Graphics and Computer-Aided Design; Computer Science Applications; Information Systems; Conservation | V9: Computer Science; Arts and Humanities | W9: Physical Sciences; Social Sciences
A10: 9 | B10: ACM Transactions on Computing Education | C10: 1531-4278 | D10: 1531-4278 | E10: 2001 | G10: Association for Computing Machinery | H10: serial | I10: https://dl.acm.org/loi/jeric | M10: General Computer Science | N10: ONOS | O10: ACM Digital Library | P10: 20894 | Q10: 145466 | R10: 1700 | S10: Inactive | T10: 2001-2009 | U10: General Computer Science | V10: Computer Science | W10: Physical Sciences
A11: 10 | B11: ACM Letters on Programming Languages and Systems | C11: 1057-4514 | D11: 1557-7384 | E11: 1979 | G11: Association for Computing Machinery | H11: serial | I11: https://dl.acm.org/loi/loplas | M11: Software | N11: ONOS | O11: ACM Digital Library | P11: 20895 | R11: 1712 | U11: Software | V11: Computer Science | W11: Physical Sciences
A12: 11 | B12: ACM Transactions on Accessible Computing | C12: 1936-7228 | D12: 1936-7236 | E12: 2008 | G12: Association for Computing Machinery | H12: serial | I12: https://dl.acm.org/loi/taccess | M12: Computer Science Applications; Human-Computer Interaction | N12: ONOS | O12: ACM Digital Library | P12: 20896 | Q12: 19700186855 | R12: 1706; 1709 | S12: Active | T12: 2008-2025 | U12: Computer Science Applications; Human-Computer Interaction | V12: Computer Science | W12: Physical Sciences
A13: 12 | B13: ACM Transactions on Algorithms | C13: 1549-6325 | D13: 1549-6333 | E13: 2005 | G13: Association for Computing Machinery | H13: serial | I13: https://dl.acm.org/loi/talg | M13: Mathematics (miscellaneous) | N13: ONOS | O13: ACM Digital Library | P13: 20897 | Q13: 4700153006 | R13: 2601 | S13: Active | T13: 2005-2026 | U13: Mathematics (miscellaneous) | V13: Mathematics | W13: Physical Sciences
A14: 13 | B14: ACM Transactions on Applied Perception | C14: 1544-3558 | D14: 1544-3965 | E14: 2004 | G14: Association for Computing Machinery | H14: serial | I14: https://dl.acm.org/loi/tap | M14: Theoretical Computer Science; Experimental and Cognitive Psychology; General Computer Science | N14: ONOS | O14: ACM Digital Library | P14: 20898 | Q14: 12100154833 | R14: 3205; 1700; 2614 | S14: Active | T14: 2004-2026 | U14: Experimental and Cognitive Psychology; General Computer Science; Theoretical Computer Science | V14: Psychology; Computer Science; Mathematics | W14: Social Sciences; Physical Sciences
A15: 14 | B15: ACM Transactions on Architecture and Code Optimization | C15: 1544-3566 | D15: 1544-3973 | E15: 2004 | G15: Association for Computing Machinery | H15: serial | I15: https://dl.acm.org/loi/taco | M15: Hardware and Architecture; Software; Information Systems | N15: ONOS | O15: ACM Digital Library | P15: 20899 | Q15: 12100154406 | R15: 1710; 1712; 1708 | S15: Active | T15: 2004-2025 | U15: Information Systems; Software; Hardware and Architecture | V15: Computer Science | W15: Physical Sciences
A16: 15 | B16: ACM Transactions on Asian and Low-Resource Language Information Processing | C16: 1530-0226 | D16: 1558-3430 | E16: 2002 | G16: Association for Computing Machinery | H16: serial | I16: https://dl.acm.org/loi/talip | M16: General Computer Science | N16: ONOS | O16: ACM Digital Library | P16: 20900 | Q16: 26798 | R16: 1700 | S16: Inactive | T16: 2002-2014 | U16: General Computer Science | V16: Computer Science | W16: Physical Sciences
A17: 16 | B17: ACM Transactions on Asian and Low-Resource Language Information Processing | C17: 2375-4699 | D17: 2375-4702 | E17: 2002 | G17: Association for Computing Machinery | H17: serial | I17: https://dl.acm.org/loi/tallip | M17: General Computer Science | N17: ONOS | O17: ACM Digital Library | P17: 20901 | Q17: 21100784666 | R17: 1700 | S17: Active | T17: 2015-2026 | U17: General Computer Science | V17: Computer Science | W17: Physical Sciences
A18: 17 | B18: ACM Transactions on Autonomous and Adaptive Systems | C18: 1556-4665 | D18: 1556-4703 | E18: 2006 | G18: Association for Computing Machinery | H18: serial | I18: https://dl.acm.org/loi/taas | M18: Software; Computer Science (miscellaneous); Control and Systems Engineering | N18: ONOS | O18: ACM Digital Library | P18: 20902 | Q18: 4800153205 | R18: 1712; 1701; 2207 | S18: Active | T18: 2006-2026 | U18: Software; Computer Science (miscellaneous); Control and Systems Engineering | V18: Computer Science; Engineering | W18: Physical Sciences
A19: 18 | B19: ACM Transactions on Computation Theory | C19: 1942-3454 | D19: 1942-3462 | E19: 2009 | G19: Association for Computing Machinery | H19: serial | I19: https://dl.acm.org/loi/toct | M19: Theoretical Computer Science; Computational Theory and Mathematics | N19: ONOS | O19: ACM Digital Library | P19: 20903 | Q19: 19700166602 | R19: 1703; 2614 | S19: Active | T19: 2009-2026 | U19: Computational Theory and Mathematics; Theoretical Computer Science | V19: Computer Science; Mathematics | W19: Physical Sciences
A20: 19 | B20: ACM Transactions on Computational Logic | C20: 1529-3785 | D20: 1557-945X | E20: 2000 | G20: Association for Computing Machinery | H20: serial | I20: https://dl.acm.org/loi/tocl | M20: Computational Mathematics; Theoretical Computer Science; Logic; General Computer Science | N20: ONOS | O20: ACM Digital Library | P20: 20904 | Q20: 23051 | R20: 2605; 2609; 1700; 2614 | S20: Active | T20: 2000-2026 | U20: Computational Mathematics; Logic; General Computer Science; Theoretical Computer Science | V20: Mathematics; Computer Science | W20: Physical Sciences
A21: 20 | B21: ACM Transactions on Computer Systems | C21: 0734-2071 | D21: 1557-7333 | E21: 1983 | G21: Association for Computing Machinery | H21: serial | I21: https://dl.acm.org/loi/tocs | M21: Software; Computer Science (miscellaneous); Control and Systems Engineering | N21: ONOS | O21: ACM Digital Library | P21: 20905 | Q21: 12213 | R21: 1700 | S21: Active | T21: 1983-2026 | U21: General Computer Science | V21: Computer Science | W21: Physical Sciences
A22: 21 | B22: ACM Transactions on Computer-Human Interaction | C22: 1073-0516 | D22: 1557-7325 | E22: 1994 | G22: Association for Computing Machinery | H22: serial | I22: https://dl.acm.org/loi/tochi | M22: Human-Computer Interaction | N22: ONOS | O22: ACM Digital Library | P22: 20906 | Q22: 26199 | R22: 1709 | S22: Active | T22: 1994-2026 | U22: Human-Computer Interaction | V22: Computer Science | W22: Physical Sciences
A23: 22 | B23: ACM Transactions on Computing Education | D23: 1946-6226 | E23: 2001 | G23: Association for Computing Machinery | H23: serial | I23: https://dl.acm.org/loi/toce | M23: Condensed Matter Physics; Mechanics of Materials; General Materials Science; General Chemistry; Mechanical Engineering | N23: ONOS | O23: ACM Digital Library | P23: 20907 | Q23: 19700183047 | R23: 3304; 1700 | S23: Active | T23: 2010-2026 | U23: Education; General Computer Science | V23: Social Sciences; Computer Science | W23: Social Sciences; Physical Sciences
A24: 23 | B24: ACM Transactions on Database Systems | C24: 0362-5915 | D24: 1557-4644 | E24: 1976 | G24: Association for Computing Machinery | H24: serial | I24: https://dl.acm.org/loi/tods | M24: Information Systems; Information Systems and Management | N24: ONOS | O24: ACM Digital Library | P24: 20908 | Q24: 13044 | R24: 1710 | S24: Active | T24: 1976-2026 | U24: Information Systems | V24: Computer Science | W24: Physical Sciences
A25: 24 | B25: ACM Transactions on Design Automation of Electronic Systems | C25: 1084-4309 | D25: 1557-7309 | E25: 1996 | G25: Association for Computing Machinery | H25: serial | I25: https://dl.acm.org/loi/todaes | M25: Computer Graphics and Computer-Aided Design; Computer Science Applications; Electrical and Electronic Engineering | N25: ONOS | O25: ACM Digital Library | P25: 20909 | Q25: 18662 | R25: 2208; 1704; 1706 | S25: Active | T25: 1996-2026 | U25: Electrical and Electronic Engineering; Computer Graphics and Computer-Aided Design; Computer Science Applications | V25: Engineering; Computer Science | W25: Physical Sciences
A26: 25 | B26: ACM Transactions on Economics and Computation | C26: 2167-8375 | D26: 2167-8383 | E26: 2013 | G26: Association for Computing Machinery | H26: serial | I26: https://dl.acm.org/loi/teac | M26: Computer Science (miscellaneous); Statistics and Probability; Computational Mathematics; Economics and Econometrics; Marketing | N26: ONOS | O26: ACM Digital Library | P26: 20910 | Q26: 21100853526 | R26: 2605; 1406; 2002; 2613; 1701 | S26: Active | T26: 2013-2026 | U26: Computational Mathematics; Marketing; Economics and Econometrics; Statistics and Probability; Computer Science (miscellaneous) | V26: Mathematics; Business, Management and Accounting; Economics, Econometrics and Finance; Computer Science | W26: Physical Sciences; Social Sciences
A27: 26 | B27: ACM Transactions on Embedded Computing Systems | C27: 1539-9087 | D27: 1558-3465 | E27: 2002 | G27: Association for Computing Machinery | H27: serial | I27: https://dl.acm.org/loi/tecs | M27: Hardware and Architecture; Software | N27: ONOS | O27: ACM Digital Library | P27: 20911 | Q27: 10300153313 | R27: 1712; 1708 | S27: Active | T27: 2002-2026 | U27: Software; Hardware and Architecture | V27: Computer Science | W27: Physical Sciences
A28: 27 | B28: ACM Transactions on Graphics | C28: 0730-0301 | D28: 1557-7368 | E28: 1982 | G28: Association for Computing Machinery | H28: serial | I28: https://dl.acm.org/loi/tog | M28: Computer Graphics and Computer-Aided Design | N28: ONOS | O28: ACM Digital Library | P28: 20912 | Q28: 24972 | R28: 1704 | S28: Active | T28: 1982-2026 | U28: Computer Graphics and Computer-Aided Design | V28: Computer Science | W28: Physical Sciences
A29: 28 | B29: ACM Transactions on Information Systems | C29: 1046-8188 | D29: 1558-2868 | E29: 1983 | G29: Association for Computing Machinery | H29: serial | I29: https://dl.acm.org/loi/tois | M29: General Business, Management and Accounting; Information Systems; Computer Science Applications | N29: ONOS | O29: ACM Digital Library | P29: 20913 | Q29: 18997 | R29: 1706; 1400; 1710 | S29: Active | T29: 1983-2026 | U29: Computer Science Applications; General Business, Management and Accounting; Information Systems | V29: Computer Science; Business, Management and Accounting | W29: Physical Sciences; Social Sciences
A30: 29 | B30: ACM Transactions on Privacy and Security | C30: 1094-9224 | D30: 1557-7406 | E30: 1998 | G30: Association for Computing Machinery | H30: serial | I30: https://dl.acm.org/loi/tissec | M30: Safety, Risk, Reliability and Quality; General Computer Science | N30: ONOS | O30: ACM Digital Library | P30: 20914 | Q30: 28875 | R30: 2213; 1700 | S30: Inactive | T30: 1999-2016 | U30: Safety, Risk, Reliability and Quality; General Computer Science | V30: Engineering; Computer Science | W30: Physical Sciences
A31: 30 | B31: ACM Transactions on Intelligent Systems and Technology | C31: 2157-6904 | D31: 2157-6912 | E31: 2010 | G31: Association for Computing Machinery | H31: serial | I31: https://dl.acm.org/loi/tist | M31: Theoretical Computer Science; Artificial Intelligence | N31: ONOS | O31: ACM Digital Library | P31: 20915 | Q31: 19700190323 | R31: 1702; 2614 | S31: Active | T31: 2010-2026 | U31: Artificial Intelligence; Theoretical Computer Science | V31: Computer Science; Mathematics | W31: Physical Sciences
A32: 31 | B32: ACM Transactions on Interactive Intelligent Systems | C32: 2160-6455 | D32: 2160-6463 | E32: 2011 | G32: Association for Computing Machinery | H32: serial | I32: https://dl.acm.org/loi/tiis | M32: Human-Computer Interaction; Artificial Intelligence | N32: ONOS | O32: ACM Digital Library | P32: 20916 | Q32: 21100301601 | R32: 1702; 1709 | S32: Active | T32: 2011-2026 | U32: Artificial Intelligence; Human-Computer Interaction | V32: Computer Science | W32: Physical Sciences
A33: 32 | B33: ACM Transactions on Internet Technology | C33: 1533-5399 | D33: 1557-6051 | E33: 2001 | G33: Association for Computing Machinery | H33: serial | I33: https://dl.acm.org/loi/toit | M33: Computer Networks and Communications | N33: ONOS | O33: ACM Digital Library | P33: 20917 | Q33: 15773 | R33: 1705 | S33: Active | T33: 2001-2026 | U33: Computer Networks and Communications | V33: Computer Science | W33: Physical Sciences
A34: 33 | B34: ACM Transactions on Knowledge Discovery from Data | C34: 1556-4681 | D34: 1556-472X | E34: 2007 | G34: Association for Computing Machinery | H34: serial | I34: https://dl.acm.org/loi/tkdd | M34: General Computer Science | N34: ONOS | O34: ACM Digital Library | P34: 20918 | Q34: 5800173377 | R34: 1700 | S34: Active | T34: 2007-2026 | U34: General Computer Science | V34: Computer Science | W34: Physical Sciences
A35: 34 | B35: ACM Transactions on Management Information Systems | C35: 2158-656X | D35: 2158-6578 | E35: 2010 | G35: Association for Computing Machinery | H35: serial | I35: https://dl.acm.org/loi/tmis | M35: General Computer Science; Management Information Systems | N35: ONOS | O35: ACM Digital Library | P35: 20919 | Q35: 21100200804 | R35: 1700; 1404 | S35: Active | T35: 2010-2026 | U35: General Computer Science; Management Information Systems | V35: Computer Science; Business, Management and Accounting | W35: Physical Sciences; Social Sciences
... A44: 43 | B44: ACM Transactions on Spatial Algorithms and Systems | C44: 2374-0353 | D44: 2374-0361 | E44: 2015 | G44: Association for Computing Machinery | H44: serial | I44: https://dl.acm.org/loi/tsas | M44: Theoretical Computer Science; Computational Theory and Mathematics | N44: ONOS | O44: ACM Digital Library | P44: 20928 | Q44: 21100857591 | R44: 2611; 2608; 2607; 1711; 1710; 1706 | S44: Active | T44: 2015-2025 | U44: Modeling and Simulation; Geometry and Topology; Discrete Mathematics and Combinatorics; Signal Processing; Information Systems; Computer Science Applications | V44: Mathematics; Computer Science | W44: Physical Sciences
A45: 44 | B45: ACM Transactions on Speech and Language Processing | C45: 1550-4875 | D45: 1550-4883 | E45: 2004 | F45: 2013 | G45: Association for Computing Machinery | H45: serial | I45: https://dl.acm.org/loi/tslp | M45: Computational Mathematics; Computer Science (miscellaneous) | N45: ONOS | O45: ACM Digital Library | P45: 20929 | Q45: 4700152720 | R45: 2605; 1701 | S45: Inactive | T45: 2004-2013 | U45: Computational Mathematics; Computer Science (miscellaneous) | V45: Mathematics; Computer Science | W45: Physical Sciences
A46: 45 | B46: ACM Transactions on Storage | C46: 1553-3077 | D46: 1553-3093 | E46: 2005 | G46: Association for Computing Machinery | H46: serial | I46: https://dl.acm.org/loi/tos | M46: Hardware and Architecture | N46: ONOS | O46: ACM Digital Library | P46: 20930 | Q46: 4700152858 | R46: 1708 | S46: Active | T46: 2005-2026 | U46: Hardware and Architecture | V46: Computer Science | W46: Physical Sciences
A47: 46 | B47: ACM Transactions on the Web | C47: 1559-1131 | D47: 1559-114X | E47: 2007 | G47: Association for Computing Machinery | H47: serial | I47: https://dl.acm.org/loi/tweb | M47: Computer Networks and Communications | N47: ONOS | O47: ACM Digital Library | P47: 20931 | Q47: 5800207369 | R47: 1705 | S47: Active | T47: 2007-2026 | U47: Computer Networks and Communications | V47: Computer Science | W47: Physical Sciences
A48: 47 | B48: IEEE/ACM Transactions on Audio, Speech and Language Processing | C48: 2329-9290 | D48: 2329-9304 | E48: 2014 | F48: 2024 | G48: Association for Computing Machinery | H48: serial | I48: https://dl.acm.org/loi/taslp | M48: Media Technology; Instrumentation; Acoustics and Ultrasonics; Linguistics and Language; Signal Processing; Electrical and Electronic Engineering; Speech and Hearing | N48: ONOS | O48: ACM Digital Library | P48: 20932 | Q48: 21100368801 | R48: 3102; 2208; 2605; 1701 | S48: Active | T48: 2014-2025 | U48: Acoustics and Ultrasonics; Electrical and Electronic Engineering; Computational Mathematics; Computer Science (miscellaneous) | V48: Physics and Astronomy; Engineering; Mathematics; Computer Science | W48: Physical Sciences
A49: 48 | B49: IEEE/ACM Transactions on Computational Biology and Bioinformatics | C49: 1545-5963 | E49: 2004 | F49: 2024 | G49: Association for Computing Machinery | H49: serial | I49: https://dl.acm.org/loi/tcbb | M49: Genetics; Applied Mathematics; Biotechnology | N49: ONOS | O49: ACM Digital Library | P49: 20933 | Q49: 17971 | R49: 2604; 1311; 1305 | S49: Inactive | T49: 2004-2024 | U49: Applied Mathematics; Genetics; Biotechnology | V49: Mathematics; Biochemistry, Genetics and Molecular Biology | W49: Physical Sciences; Life Sciences
A50: 49 | B50: IEEE/ACM Transactions on Networking | C50: 1063-6692 | E50: 1993 | F50: 2024 | G50: Association for Computing Machinery | H50: serial | I50: https://dl.acm.org/loi/ton | M50: Software; Computer Networks and Communications; Computer Science Applications; Electrical and Electronic Engineering | N50: ONOS | O50: ACM Digital Library | P50: 20934 | Q50: 27237 | R50: 1705; 1706; 1712; 2208 | S50: Inactive | T50: 1993-2024 | U50: Computer Networks and Communications; Computer Science Applications; Software; Electrical and Electronic Engineering | V50: Computer Science; Engineering | W50: Physical Sciences
A51: 50 | B51: ACM Inroads | C51: 2153-2184 | D51: 2153-2192 | E51: 2010 | G51: Association for Computing Machinery | H51: serial | I51: https://dl.acm.org/loi/inroads | M51: General Computer Science; Education | N51: ONOS | O51: ACM Digital Library | P51: 20935 | Q51: 19700201136 | R51: 3304; 1700 | S51: Active | T51: 2010-2026 | U51: Education; General Computer Science | V51: Social Sciences; Computer Science | W51: Social Sciences; Physical Sciences
A52: 51 | B52: Communications of the ACM | C52: 0001-0782 | D52: 1557-7317 | E52: 1958 | G52: Association for Computing Machinery | H52: serial | I52: https://dl.acm.org/loi/cacm | M52: General Computer Science | N52: ONOS | O52: ACM Digital Library | P52: 20936 | Q52: 13675 | R52: 1700 | S52: Active | T52: 1958-2026 | U52: General Computer Science | V52: Computer Science | W52: Physical Sciences
A53: 52 | B53: Computers in Entertainment | D53: 1544-3574 | E53: 2003 | F53: 2018 | G53: Association for Computing Machinery | H53: serial | I53: https://dl.acm.org/loi/cie | M53: Condensed Matter Physics; Mechanics of Materials; General Materials Science; General Chemistry; Mechanical Engineering | N53: ONOS | O53: ACM Digital Library | P53: 20937 | Q53: 4700152823 | R53: 1706 | S53: Inactive | T53: 2016-2018; 2014; 2005-2012 | U53: Computer Science Applications | V53: Computer Science | W53: Physical Sciences
A54: 53 | B54: XRDS: Crossroads, The ACM Magazine for Students | D54: 1528-4980 | E54: 2010 | G54: Association for Computing Machinery | H54: serial | I54: https://dl.acm.org/loi/xrds | M54: Condensed Matter Physics; Mechanics of Materials; General Materials Science; General Chemistry; Mechanical Engineering | N54: ONOS | O54: ACM Digital Library | P54: 20938 | R54: 3104; 2211; 2500; 1600; 2210 | U54: Condensed Matter Physics; Mechanics of Materials; General Materials Science; General Chemistry; Mechanical Engineering | V54: Physics and Astronomy; Engineering; Materials Science; Chemistry | W54: Physical Sciences
A55: 54 | B55: Queue | C55: 1542-7730 | D55: 1542-7749 | E55: 2003 | G55: Association for Computing Machinery | H55: serial | I55: https://dl.acm.org/loi/queue | M55: General Computer Science | N55: ONOS | O55: ACM Digital Library | P55: 20939 | Q55: 19700186817 | R55: 1700 | S55: Active | T55: 2003-2025 | U55: General Computer Science | V55: Computer Science | W55: Physical Sciences
A56: 55 | B56: StandardView | C56: 1067-9936 | D56: 1557-7376 | E56: 1993 | F56: 1998 | G56: Association for Computing Machinery | H56: serial | I56: https://dl.acm.org/loi/standardview | M56: Hardware and Architecture; Computer Networks and Communications | N56: ONOS | O56: ACM Digital Library | P56: 20940 | R56: 1708; 1705 | U56: Hardware and Architecture; Computer Networks and Communications | V56: Computer Science | W56: Physical Sciences
A57: 56 | B57: Ubiquity | D57: 1530-2180 | E57: 2000 | G57: Association for Computing Machinery | H57: serial | I57: https://dl.acm.org/loi/ubiquity | M57: Condensed Matter Physics; Mechanics of Materials; General Materials Science; General Chemistry; Mechanical Engineering | N57: ONOS | O57: ACM Digital Library | P57: 20941 | R57: 3104; 2211; 2500; 1600; 2210 | U57: Condensed Matter Physics; Mechanics of Materials; General Materials Science; General Chemistry; Mechanical Engineering | V57: Physics and Astronomy; Engineering; Materials Science; Chemistry | W57: Physical Sciences
A58: 57 | B58: Crossroads | C58: 1528-4972 | E58: 1994 | F58: 2010 | G58: Association for Computing Machinery | H58: serial | I58: https://dl.acm.org/toc/xrds/2010/ | M58: Condensed Matter Physics; Mechanics of Materials; General Materials Science; General Chemistry; Mechanical Engineering | N58: ONOS | O58: ACM Digital Library | P58: 20942 | R58: 3104; 2211; 2500; 1600; 2210 | U58: Condensed Matter Physics; Mechanics of Materials; General Materials Science; General Chemistry; Mechanical Engineering | V58: Physics and Astronomy; Engineering; Materials Science; Chemistry | W58: Physical Sciences
A59: 58 | B59: eLearn | D59: 1535-394X | E59: 2001 | G59: Association for Computing Machinery | H59: serial | I59: https://dl.acm.org/loi/elearn | M59: Condensed Matter Physics; Mechanics of Materials; General Materials Science; General Chemistry; Mechanical Engineering | N59: ONOS | O59: ACM Digital Library | P59: 20943 | R59: 3104; 2211; 2500; 1600; 2210 | U59: Condensed Matter Physics; Mechanics of Materials; General Materials Science; General Chemistry; Mechanical Engineering | V59: Physics and Astronomy; Engineering; Materials Science; Chemistry | W59: Physical Sciences
A60: 59 | B60: intelligence | C60: 1523-8822 | D60: 1557-9425 | E60: 1970 | F60: 2001 | G60: Association for Computing Machinery | H60: serial | I60: https://dl.acm.org/loi/intelligence | M60: Experimental and Cognitive Psychology | N60: ONOS | O60: ACM Digital Library | P60: 20944 | R60: 3205 | U60: Experimental and Cognitive Psychology | V60: Psychology | W60: Social Sciences
A61: 60 | B61: interactions | C61: 1072-5520 | D61: 1558-3449 | E61: 1994 | G61: Association for Computing Machinery | H61: serial | I61: https://dl.acm.org/loi/interactions | M61: Human-Computer Interaction | N61: ONOS | O61: ACM Digital Library | P61: 20945 | Q61: 4000148705 | R61: 1709 | S61: Active | T61: 2006-2026; 1997-1998; 1994-1995 | U61: Human-Computer Interaction | V61: Computer Science | W61: Physical Sciences
A62: 61 | B62: netWorker | C62: 1091-3556 | D62: 1558-3473 | E62: 1997 | F62: 2009 | G62: Association for Computing Machinery | H62: serial | I62: https://dl.acm.org/loi/networker | M62: Computer Networks and Communications | N62: ONOS | O62: ACM Digital Library | P62: 20946 | R62: 1705 | U62: Computer Networks and Communications | V62: Computer Science | W62: Physical Sciences
A63: 62 | B63: ALGOL Bulletin | C63: 0084-6198 | E63: 1959 | F63: 1988 | G63: Association for Computing Machinery | H63: serial | I63: https://dl.acm.org/loi/algol | M63: Software | N63: ONOS | O63: ACM Digital Library | P63: 20947 | R63: 1712 | U63: Software | V63: Computer Science | W63: Physical Sciences
A64: 63 | B64: Computational Linguistics | C64: 0891-2017 | D64: 1530-9312 | E64: 1980 | F64: 2020 | G64: Association for Computing Machinery | H64: serial | I64: https://dl.acm.org/loi/coli | M64: Artificial Intelligence; Linguistics and Language; Language and Linguistics; Computer Science Applications | N64: ONOS | O64: ACM Digital Library | P64: 20948 | Q64: 26801 | R64: 3310; 1702; 1706; 1203 | S64: Active | T64: 1996-2025; 1985-1986 | U64: Linguistics and Language; Artificial Intelligence; Computer Science Applications; Language and Linguistics | V64: Social Sciences; Computer Science; Arts and Humanities | W64: Social Sciences; Physical Sciences
A65: 64 | B65: Evolutionary Computation | C65: 1063-6560 | D65: 1530-9304 | E65: 1993 | F65: 2020 | G65: Association for Computing Machinery | H65: serial | I65: https://dl.acm.org/loi/evol | M65: Computational Mathematics | N65: ONOS | O65: ACM Digital Library | P65: 20949 | Q65: 24966 | R65: 2605 | S65: Active | T65: 1995-2026 | U65: Computational Mathematics | V65: Mathematics | W65: Physical Sciences
A66: 65 | B66: Journal of Computing Sciences in Colleges | C66: 1937-4771 | D66: 1937-4763 | E66: 1991 | G66: Association for Computing Machinery | H66: serial | I66: https://dl.acm.org/loi/jcsc | M66: General Computer Science; Education | N66: ONOS | O66: ACM Digital Library | P66: 20950 | R66: 1700; 3304 | U66: General Computer Science; Education | V66: Computer Science; Social Sciences | W66: Physical Sciences; Social Sciences
A67: 66 | B67: Journal of Usability Studies | C67: 1931-3357 | E67: 2005 | G67: Association for Computing Machinery | H67: serial | I67: https://dl.acm.org/loi/jus | M67: General Engineering | N67: ONOS | O67: ACM Digital Library | P67: 20951 | R67: 2200 | U67: General Engineering | V67: Engineering | W67: Physical Sciences
A68: 67 | B68: Linux Journal | C68: 1075-3583 | E68: 1994 | F68: 2017 | G68: Association for Computing Machinery | H68: serial | I68: https://dl.acm.org/loi/linux | M68: Software | N68: ONOS | O68: ACM Digital Library | P68: 20952 | R68: 1712 | U68: Software | V68: Computer Science | W68: Physical Sciences
A69: 68 | B69: Personal and Ubiquitous Computing | C69: 1617-4909 | E69: 2000 | G69: Association for Computing Machinery | H69: serial | I69: https://dl.acm.org/loi/puc | M69: Hardware and Architecture; Management Science and Operations Research; Computer Science Applications | N69: ONOS | O69: ACM Digital Library | P69: 20953 | Q69: 22315 | R69: 3309; 1803; 1706; 1708 | S69: Active | T69: 1997-2026 | U69: Library and Information Sciences; Management Science and Operations Research; Computer Science Applications; Hardware and Architecture | V69: Social Sciences; Decision Sciences; Computer Science | W69: Social Sciences; Physical Sciences
A70: 69 | B70: Proceedings of the VLDB Endowment | C70: 2150-8097 | E70: 2008 | G70: Association for Computing Machinery | H70: serial | I70: https://dl.acm.org/loi/pvldb | M70: Information Systems; Information Systems and Management | N70: ONOS | O70: ACM Digital Library | P70: 20954 | Q70: 21100199855 | R70: 1701; 1700 | S70: Active | T70: 2008-2025 | U70: Computer Science (miscellaneous); General Computer Science | V70: Computer Science | W70: Physical Sciences
A71: 70 | B71: The Journal of Machine Learning Research | C71: 1532-4435 | D71: 1533-7928 | E71: 2001 | G71: Association for Computing Machinery | H71: serial | I71: https://dl.acm.org/loi/jmlr | M71: Artificial Intelligence; Software; Statistics and Probability; Control and Systems Engineering | N71: ONOS | O71: ACM Digital Library | P71: 20955 | Q71: 20969 | R71: 2207; 1712; 1702; 2613 | S71: Active | T71: 2001-2026 | U71: Control and Systems Engineering; Software; Artificial Intelligence; Statistics and Probability | V71: Engineering; Computer Science; Mathematics | W71: Physical Sciences
A72: 71 | B72: The VLDB Journal - The International Journal on Very Large Data Bases | C72: 1066-8888 | E72: 1992 | G72: Association for Computing Machinery | H72: serial | I72: https://dl.acm.org/journal/vldb | M72: Hardware and Architecture; Information Systems | N72: ONOS | O72: ACM Digital Library | P72: 20956 | Q72: 13646 | R72: 1708; 1710 | S72: Active | T72: 1992-2026 | U72: Hardware and Architecture; Information Systems | V72: Computer Science | W72: Physical Sciences
A73: 72 | B73: 3C ON-LINE | C73: 1078-2192 | E73: 1994 | F73: 1997 | G73: Association for Computing Machinery | H73: serial | I73: https://dl.acm.org/loi/sig3c | M73: Hardware and Architecture; Software; Electrical and Electronic Engineering | N73: ONOS | O73: ACM Digital Library | P73: 20957 | R73: 1708; 1712; 2208 | U73: Hardware and Architecture; Software; Electrical and Electronic Engineering | V73: Computer Science; Engineering | W73: Physical Sciences
A74: 73 | B74: ACM Communications in Computer Algebra | C74: 1932-2240 | E74: 1967 | G74: Association for Computing Machinery | H74: serial | I74: https://dl.acm.org/loi/sigsam-cca | M74: Computational Mathematics; Computational Theory and Mathematics | N74: ONOS | O74: ACM Digital Library | P74: 20958 | Q74: 21100198457 | R74: 2605; 1703 | S74: Active | T74: 2011-2025 | U74: Computational Mathematics; Computational Theory and Mathematics | V74: Mathematics; Computer Science | W74: Physical Sciences
A75: 74 | B75: ACM Lisp Bulletin | E75: 1969 | F75: 1979 | G75: Association for Computing Machinery | H75: serial | I75: https://dl.acm.org/loi/sigplan-lisp | M75: Condensed Matter Physics; Mechanics of Materials; General Materials Science; General Chemistry; Mechanical Engineering | N75: ONOS | O75: ACM Digital Library | P75: 20959 | R75: 3104; 2211; 2500; 1600; 2210 | U75: Condensed Matter Physics; Mechanics of Materials; General Materials Science; General Chemistry; Mechanical Engineering | V75: Physics and Astronomy; Engineering; Materials Science; Chemistry | W75: Physical Sciences
A76: 75 | B76: ACM SIGACCESS Accessibility and Computing | C76: 1558-2337 | D76: 1558-1187 | E76: 2003 | G76: Association for Computing Machinery | H76: serial | I76: https://dl.acm.org/loi/sigaccess | M76: General Social Sciences; General Computer Science | N76: ONOS | O76: ACM Digital Library | P76: 20960 | R76: 3300; 1700 | U76: General Social Sciences; General Computer Science | V76: Social Sciences; Computer Science | W76: Social Sciences; Physical Sciences
A77: 76 | B77: ACM SIGACT News | C77: 0163-5700 | E77: 1969 | G77: Association for Computing Machinery | H77: serial | I77: https://dl.acm.org/loi/sigact | M77: General Computer Science; General Engineering | N77: ONOS | O77: ACM Digital Library | P77: 20961 | R77: 1700; 2200 | U77: General Computer Science; General Engineering | V77: Computer Science; Engineering | W77: Physical Sciences
A78: 77 | B78: ACM SIGAPL APL Quote Quad | C78: 0163-6006 | E78: 1971 | F78: 2007 | G78: Association for Computing Machinery | H78: serial | I78: https://dl.acm.org/loi/sigapl | M78: Software; Computer Science (miscellaneous) | N78: ONOS | O78: ACM Digital Library | P78: 20962 | R78: 1712; 1701 | U78: Software; Computer Science (miscellaneous) | V78: Computer Science | W78: Physical Sciences
A79: 78 | B79: ACM SIGAPP Applied Computing Review | C79: 1559-6915 | D79: 1931-0161 | E79: 1993 | G79: Association for Computing Machinery | H79: serial | I79: https://dl.acm.org/loi/sigapp | M79: Software | N79: ONOS | O79: ACM Digital Library | P79: 20963 | R79: 1712 | U79: Software | V79: Computer Science | W79: Physical Sciences
A80: 79 | B80: ACM SIGARCH Computer Architecture News | C80: 0163-5964 | E80: 1972 | F80: 2017 | G80: Association for Computing Machinery | H80: serial | I80: https://dl.acm.org/loi/sigarch | M80: Hardware and Architecture | N80: ONOS | O80: ACM Digital Library | P80: 20964 | R80: 1708 | U80: Hardware and Architecture | V80: Computer Science | W80: Physical Sciences
A81: 80 | B81: ACM SIGART Bulletin | C81: 0163-5719 | E81: 1970 | F81: 2001 | G81: Association for Computing Machinery | H81: serial | I81: https://dl.acm.org/loi/sigai | M81: Experimental and Cognitive Psychology | N81: ONOS | O81: ACM Digital Library | P81: 20965 | R81: 3205 | U81: Experimental and Cognitive Psychology | V81: Psychology | W81: Social Sciences
A82: 81 | B82: ACM SIGAda Ada Letters | C82: 1094-3641 | E82: 1981 | G82: Association for Computing Machinery | H82: serial | I82: https://dl.acm.org/loi/sigada | M82: Software | N82: ONOS | O82: ACM Digital Library | P82: 20966 | R82: 1712 | U82: Software | V82: Computer Science | W82: Physical Sciences
A83: 82 | B83: ACM SIGBED Review | D83: 1551-3688 | E83: 2004 | F83: 2020 | G83: Association for Computing Machinery | H83: serial | I83: https://dl.acm.org/loi/sigbed | M83: Condensed Matter Physics; Mechanics of Materials; General Materials Science; General Chemistry; Mechanical Engineering | N83: ONOS | O83: ACM Digital Library | P83: 20967 | Q83: 21100900336 | R83: 2201; 1701 | S83: Inactive | T83: 2017-2020; 2011; 2007-2009 | U83: Engineering (miscellaneous); Computer Science (miscellaneous) | V83: Engineering; Computer Science | W83: Physical Sciences
A84: 83 | B84: ACM SIGBIO Newsletter | C84: 0163-5697 | E84: 1976 | F84: 2001 | G84: Association for Computing Machinery | H84: serial | I84: https://dl.acm.org/loi/sigbio-news | M84: General Medicine; General Computer Science | N84: ONOS | O84: ACM Digital Library | P84: 20968 | R84: 2700; 1700 | U84: General Medicine; General Computer Science | V84: Medicine; Computer Science | W84: Health Sciences; Physical Sciences
A85: 84 | B85: ACM SIGBioinformatics Record | C85: 2331-9291 | D85: 2159-1210 | E85: 2011 | G85: Association for Computing Machinery | H85: serial | I85: https://dl.acm.org/loi/sigbio | M85: Biomedical Engineering; General Medicine | N85: ONOS | O85: ACM Digital Library | P85: 20969 | R85: 2204; 2700 | U85: Biomedical Engineering; General Medicine | V85: Engineering; Medicine | W85: Physical Sciences; Health Sciences
A86: 85 | B86: ACM SIGCAPH Computers and the Physically Handicapped | C86: 0163-5727 | E86: 1971 | F86: 2003 | G86: Association for Computing Machinery | H86: serial | I86: https://dl.acm.org/loi/sigaccess-sigcaph | M86: General Social Sciences; General Computer Science | N86: ONOS | O86: ACM Digital Library | P86: 20970 | R86: 3300; 1700 | U86: General Social Sciences; General Computer Science | V86: Social Sciences; Computer Science | W86: Social Sciences; Physical Sciences
A87: 86 | B87: ACM SIGCAS Computers and Society | C87: 0095-2737 | E87: 1970 | F87: 2024 | G87: Association for Computing Machinery | H87: serial | I87: https://dl.acm.org/loi/sigcas | M87: Sociology and Political Science; Computer Science Applications | N87: ONOS | O87: ACM Digital Library | P87: 20971 | R87: 3312; 1706 | U87: Sociology and Political Science; Computer Science Applications | V87: Social Sciences; Computer Science | W87: Social Sciences; Physical Sciences
A88: 87 | B88: ACM SIGCHI Bulletin | C88: 0736-6906 | E88: 1982 | F88: 2000 | G88: Association for Computing Machinery | H88: serial | I88: https://dl.acm.org/loi/sigchi | M88: Sociology and Political Science; Computer Science Applications | N88: ONOS | O88: ACM Digital Library | P88: 20972 | R88: 3312; 1706 | U88: Sociology and Political Science; Computer Science Applications | V88: Social Sciences; Computer Science | W88: Social Sciences; Physical Sciences
A89: 88 | B89: ACM SIGCHI Bulletin - a supplement to <i>interactions</i> | D89: 1558-1217 | E89: 2000 | F89: 2003 | G89: Association for Computing Machinery | H89: serial | I89: https://dl.acm.org/loi/sigchi-suppl | M89: Sociology and Political Science; Computer Science Applications | N89: ONOS | O89: ACM Digital Library | P89: 20973 | R89: 3312; 1706 | U89: Sociology and Political Science; Computer Science Applications | V89: Social Sciences; Computer Science | W89: Social Sciences; Physical Sciences
A90: 89 | B90: ACM SIGCOMM Computer Communication Review | C90: 0146-4833 | E90: 1970 | G90: Association for Computing Machinery | H90: serial | I90: https://dl.acm.org/loi/sigcomm-ccr | M90: Hardware and Architecture; Computer Networks and Communications | N90: ONOS | O90: ACM Digital Library | P90: 20974 | Q90: 13683 | R90: 1705; 1712 | S90: Active | T90: 1994-2025; 1988-1989; 1985 | U90: Computer Networks and Communications; Software | V90: Computer Science | W90: Physical Sciences
A91: 90 | B91: ACM SIGCPR Computer Personnel | C91: 0160-2497 | E91: 1964 | F91: 1999 | G91: Association for Computing Machinery | H91: serial | I91: https://dl.acm.org/loi/sigcpr | M91: Condensed Matter Physics; Mechanics of Materials; General Materials Science; General Chemistry; Mechanical Engineering | N91: ONOS | O91: ACM Digital Library | P91: 20975 | R91: 3104; 2211; 2500; 1600; 2210 | U91: Condensed Matter Physics; Mechanics of Materials; General Materials Science; General Chemistry; Mechanical Engineering | V91: Physics and Astronomy; Engineering; Materials Science; Chemistry | W91: Physical Sciences
A92: 91 | B92: ACM SIGCSE Bulletin | C92: 0097-8418 | E92: 1969 | G92: Association for Computing Machinery | H92: serial | I92: https://dl.acm.org/loi/sigcse | M92: General Computer Science; Education | N92: ONOS | O92: ACM Digital Library | P92: 20976 | R92: 1700; 3304 | U92: General Computer Science; Education | V92: Computer Science; Social Sciences | W92: Physical Sciences; Social Sciences
A93: 92 | B93: ACM SIGCSIM Installation Management Review | C93: 0163-5972 | E93: 1969 | F93: 1977 | G93: Association for Computing Machinery | H93: serial | I93: https://dl.acm.org/loi/sigcsim | M93: General Computer Science; General Engineering | N93: ONOS | O93: ACM Digital Library | P93: 20977 | R93: 1700; 2200 | U93: General Computer Science; General Engineering | V93: Computer Science; Engineering | W93: Physical Sciences
A94: 93 | B94: ACM SIGCUE Outlook | C94: 0163-5735 | E94: 1970 | F94: 2001 | G94: Association for Computing Machinery | H94: serial | I94: https://dl.acm.org/loi/sigcue | M94: General Computer Science; Education | N94: ONOS | O94: ACM Digital Library | P94: 20978 | R94: 1700; 3304 | U94: General Computer Science; Education | V94: Computer Science; Social Sciences | W94: Physical Sciences; Social Sciences
A95: 94 | B95: ACM SIGDA Newsletter | C95: 0163-5743 | E95: 1971 | F95: 2010 | G95: Association for Computing Machinery | H95: serial | I95: https://dl.acm.org/loi/sigda | M95: Computer Science Applications | N95: ONOS | O95: ACM Digital Library | P95: 20979 | R95: 1706 | U95: Computer Science Applications | V95: Computer Science | W95: Physical Sciences
A96: 95 | B96: ACM SIGDOC Asterisk Journal of Computer Documentation | C96: 0731-1001 | E96: 1975 | F96: 1999 | G96: Association for Computing Machinery | H96: serial | I96: https://dl.acm.org/loi/sigdoc | M96: General Computer Science | N96: ONOS | O96: ACM Digital Library | P96: 20980 | R96: 1700 | U96: General Computer Science | V96: Computer Science | W96: Physical Sciences
A97: 96 | B97: ACM SIGEVOlution | D97: 1931-8499 | E97: 2006 | G97: Association for Computing Machinery | H97: serial | I97: https://dl.acm.org/loi/sigevo | M97: Condensed Matter Physics; Mechanics of Materials; General Materials Science; General Chemistry; Mechanical Engineering | N97: ONOS | O97: ACM Digital Library | P97: 20981 | R97: 3104; 2211; 2500; 1600; 2210 | U97: Condensed Matter Physics; Mechanics of Materials; General Materials Science; General Chemistry; Mechanical Engineering | V97: Physics and Astronomy; Engineering; Materials Science; Chemistry | W97: Physical Sciences
A98: 97 | B98: ACM SIGFORTH Newsletter | C98: 1047-4544 | E98: 1989 | F98: 1994 | G98: Association for Computing Machinery | H98: serial | I98: https://dl.acm.org/loi/sigforth | M98: Condensed Matter Physics; Mechanics of Materials; General Materials Science; General Chemistry; Mechanical Engineering | N98: ONOS | O98: ACM Digital Library | P98: 20982 | R98: 3104; 2211; 2500; 1600; 2210 | U98: Condensed Matter Physics; Mechanics of Materials; General Materials Science; General Chemistry; Mechanical Engineering | V98: Physics and Astronomy; Engineering; Materials Science; Chemistry | W98: Physical Sciences
A99: 98 | B99: ACM SIGGRAPH Computer Graphics | C99: 0097-8930 | E99: 1960 | F99: 2011 | G99: Association for Computing Machinery | H99: serial | I99: https://dl.acm.org/loi/siggraph | M99: Computer Graphics and Computer-Aided Design | N99: ONOS | O99: ACM Digital Library | P99: 20983 | Q99: 34597 | R99: 1704 | S99: Inactive | T99: 1992-2011; 1990; 1978-1988 | U99: Computer Graphics and Computer-Aided Design | V99: Computer Science | W99: Physical Sciences
A100: 99 | B100: ACM SIGGROUP Bulletin | C100: 2372-7403 | D100: 2372-739X | E100: 1997 | F100: 2005 | G100: Association for Computing Machinery | H100: serial | I100: https://dl.acm.org/loi/siggroup | M100: Computer Science (miscellaneous); Statistics and Probability; Computational Mathematics; Economics and Econometrics; Marketing | N100: ONOS | O100: ACM Digital Library | P100: 20984 | R100: 1701; 2613; 2605; 2002; 1406 | U100: Computer Science (miscellaneous); Statistics and Probability; Computational Mathematics; Economics and Econometrics; Marketing | V100: Computer Science; Mathematics; Economics, Econometrics and Finance; Business, Management and Accounting | W100: Physical Sciences; Social Sciences
A101: 100 | B101: ACM SIGHIT Record | D101: 2158-8813 | E101: 2011 | F101: 2012 | G101: Association for Computing Machinery | H101: serial | I101: https://dl.acm.org/loi/sighit | M101: Condensed Matter Physics; Mechanics of Materials; General Materials Science; General Chemistry; Mechanical Engineering | N101: ONOS | O101: ACM Digital Library | P101: 20985 | R101: 3104; 2211; 2500; 1600; 2210 | U101: Condensed Matter Physics; Mechanics of Materials; General Materials Science; General Chemistry; Mechanical Engineering | V101: Physics and Astronomy; Engineering; Materials Science; Chemistry | W101: Physical Sciences
A102: 101 | B102: ACM SIGHPC Connect | D102: 2168-135X | E102: 2012 | F102: 2023 | G102: Association for Computing Machinery | H102: serial | I102: https://dl.acm.org/loi/sighpc | M102: Condensed Matter Physics; Mechanics of Materials; General Materials Science; General Chemistry; Mechanical Engineering | N102: ONOS | O102: ACM Digital Library | P102: 20986 | R102: 3104; 2211; 2500; 1600; 2210 | U102: Condensed Matter Physics; Mechanics of Materials; General Materials Science; General Chemistry; Mechanical Engineering | V102: Physics and Astronomy; Engineering; Materials Science; Chemistry | W102: Physical Sciences
A103: 102 | B103: ACM SIGICE Bulletin | C103: 1558-1144 | E103: 1994 | F103: 1997 | G103: Association for Computing Machinery | H103: serial | I103: https://dl.acm.org/loi/sigice | M103: General Computer Science | N103: ONOS | O103: ACM Digital Library | P103: 20987 | R103: 1700 | U103: General Computer Science | V103: Computer Science | W103: Physical Sciences
A104: 103 | B104: ACM SIGIR Forum | C104: 0163-5840 | E104: 1971 | F104: 2024 | G104: Association for Computing Machinery | H104: serial | I104: https://dl.acm.org/loi/sigir | M104: General Computer Science | N104: ONOS | O104: ACM Digital Library | P104: 20988 | Q104: 15745 | R104: 1708; 1404 | S104: Active | T104: 2024-2025; 2019-2020; 2013; 2009; 1985-2003; 1971-1983 | U104: Hardware and Architecture; Management Information Systems | V104: Computer Science; Business, Management and Accounting | W104: Physical Sciences; Social Sciences
A105: 104 | B105: ACM SIGITE Newsletter | C105: 2166-1685 | D105: 1550-1469 | E105: 2005 | F105: 2019 | G105: Association for Computing Machinery | H105: serial | I105: https://dl.acm.org/loi/sigite | M105: Condensed Matter Physics; Mechanics of Materials; General Materials Science; General Chemistry; Mechanical Engineering | N105: ONOS | O105: ACM Digital Library | P105: 20989 | R105: 3104; 2211; 2500; 1600; 2210 | U105: Condensed Matter Physics; Mechanics of Materials; General Materials Science; General Chemistry; Mechanical Engineering | V105: Physics and Astronomy; Engineering; Materials Science; Chemistry | W105: Physical Sciences
A106: 105 | B106: ACM SIGITE Research in IT | D106: 1944-0278 | E106: 2005 | F106: 2019 | G106: Association for Computing Machinery | H106: serial | I106: https://dl.acm.org/loi/sigite-riit | M106: Condensed Matter Physics; Mechanics of Materials; General Materials Science; General Chemistry; Mechanical Engineering | N106: ONOS | O106: ACM Digital Library | P106: 20990 | R106: 3104; 2211; 2500; 1600; 2210 | U106: Condensed Matter Physics; Mechanics of Materials; General Materials Science; General Chemistry; Mechanical Engineering | V106: Physics and Astronomy; Engineering; Materials Science; Chemistry | W106: Physical Sciences
A107: 106 | B107: ACM SIGKDD Explorations Newsletter | C107: 1931-0145 | D107: 1931-0153 | E107: 1999 | G107: Association for Computing Machinery | H107: serial | I107: https://dl.acm.org/loi/sigkdd | M107: Condensed Matter Physics; Mechanics of Materials; General Materials Science; General Chemistry; Mechanical Engineering | N107: ONOS | O107: ACM Digital Library | P107: 20991 | R107: 3104; 2211; 2500; 1600; 2210 | U107: Condensed Matter Physics; Mechanics of Materials; General Materials Science; General Chemistry; Mechanical Engineering | V107: Physics and Astronomy; Engineering; Materials Science; Chemistry | W107: Physical Sciences
A108: 107 | B108: ACM SIGLASH Newsletter | C108: 0036-147X | D108: 1931-1095 | E108: 1979 | F108: 1981 | G108: Association for Computing Machinery | H108: serial | I108: https://dl.acm.org/loi/siglash | M108: General Social Sciences; General Computer Science | N108: ONOS | O108: ACM Digital Library | P108: 20992 | R108: 3300; 1700 | U108: General Social Sciences; General Computer Science | V108: Social Sciences; Computer Science | W108: Social Sciences; Physical Sciences
...

Sheet Sheet7
A1: sr.no. | B1: publication_title | C1: issn | D1: eissn | E1: date_first_issue_online | F1: date_last_issue_online | G1: publisher_name | H1: publication_type | I1: title_url | J1: title_id | K1: coverage_depth | L1: coverage_notes | M1: subjectname | N1: provider_name | O1: collectionname | P1: id | Q1: scopusid | R1: asjc codes_y | S1: active or inactive_y | T1: coverage_y | U1: Subject Keywords | V1: Main Subject | W1: Supergroup
A2: 13639 | B2: AEA Papers and Proceedings | C2: 2574-0768 | D2: 2574-0776 | E2: 2018 | F2: 2023 | G2: American Economic Association | H2: serial | I2: https://www.jstor.org/journal/aeapapeproc | J2: aeapapeproc | M2: =VLOOKUP(B2,[1]Sheet2!A:G, 2, FALSE) -> Economics | N2: IITGN | O2: JSTOR | R2: =VLOOKUP(B2,[1]Sheet2!A:G, 4, FALSE) -> 2002 | U2: =VLOOKUP(B2,[1]Sheet2!A:G, 5, FALSE) -> Economics and Econometrics | V2: =VLOOKUP(B2,[1]Sheet2!A:G, 6, FALSE) -> Economics, Econometrics and Finance | W2: =VLOOKUP(B2,[1]Sheet2!A:G, 7, FALSE) -> Social Sciences
A3: 13923 | B3: The Annual of ASOR | C3: 2993-7116 | D3: 2993-7124 | E3: 2021 | F3: 2021 | G3: The American Society Of Overseas Research (ASOR) | H3: serial | I3: https://www.jstor.org/journal/annualasor | J3: annualasor | K3: No issues were published from 2022-2023. Vol. 75 (2024) will be released in 2028. | M3: =VLOOKUP(B3,[1]Sheet2!A:G, 2, FALSE) -> Archaeology / Near Eastern Studies | N3: IITGN | O3: JSTOR | R3: =VLOOKUP(B3,[1]Sheet2!A:G, 4, FALSE) -> 1206 | U3: =VLOOKUP(B3,[1]Sheet2!A:G, 5, FALSE) -> Archaeology | V3: =VLOOKUP(B3,[1]Sheet2!A:G, 6, FALSE) -> Arts and Humanities | W3: =VLOOKUP(B3,[1]Sheet2!A:G, 7, FALSE) -> Social Sciences
A4: 13982 | B4: Antropología Americana | C4: 2521-7607 | D4: 2521-7615 | E4: 2016 | F4: 2020 | G4: Pan American Institute of Geography and History | H4: serial | I4: https://www.jstor.org/journal/antramer | J4: antramer | M4: =VLOOKUP(B4,[1]Sheet2!A:G, 2, FALSE) -> Anthropology | N4: IITGN | O4: JSTOR | R4: =VLOOKUP(B4,[1]Sheet2!A:G, 4, FALSE) -> 3314 | U4: =VLOOKUP(B4,[1]Sheet2!A:G, 5, FALSE) -> Anthropology | V4: =VLOOKUP(B4,[1]Sheet2!A:G, 6, FALSE) -> Social Sciences | W4: =VLOOKUP(B4,[1]Sheet2!A:G, 7, FALSE) -> Social Sciences
A5: 14018 | B5: Architectural Association Quarterly (AAQ) | C5: 0001-0189 | E5: 1969 | F5: 1982 | G5: Architectural Association School of Architecture | H5: serial | I5: https://www.jstor.org/journal/archassoquar | J5: archassoquar | K5: Content for this title is released as soon as the latest issues become available to JSTOR. | M5: =VLOOKUP(B5,[1]Sheet2!A:G, 2, FALSE) -> Architecture / Design | N5: IITGN | O5: JSTOR | R5: =VLOOKUP(B5,[1]Sheet2!A:G, 4, FALSE) -> 2210; 1203 | U5: =VLOOKUP(B5,[1]Sheet2!A:G, 5, FALSE) -> Architecture; Visual Arts and Performing Arts | V5: =VLOOKUP(B5,[1]Sheet2!A:G, 6, FALSE) -> Engineering; Arts and Humanities | W5: =VLOOKUP(B5,[1]Sheet2!A:G, 7, FALSE) -> Physical Sciences; Social Sciences
A6: 14137 | B6: Atlantisch Nieuws | C6: 0167-1898 | D6: 2949-8171 | E6: 1980 | F6: 1990 | G6: Stichting Atlantische Commissie | H6: serial | I6: https://www.jstor.org/journal/atlantischnieuws | J6: atlantischnieuws | K6: Coverage for this title ends with Vol. 49, No. 2 (2025) | M6: =VLOOKUP(B6,[1]Sheet2!A:G, 2, FALSE) -> Regional / Cultural Studies | N6: IITGN | O6: JSTOR | R6: =VLOOKUP(B6,[1]Sheet2!A:G, 4, FALSE) -> 1202 | U6: =VLOOKUP(B6,[1]Sheet2!A:G, 5, FALSE) -> Cultural Studies | V6: =VLOOKUP(B6,[1]Sheet2!A:G, 6, FALSE) -> Arts and Humanities | W6: =VLOOKUP(B6,[1]Sheet2!A:G, 7, FALSE) -> Social Sciences
A7: 14138 | B7: Atlantisch Nieuws | C7: 0167-1898 | D7: 2949-8171 | E7: 1991 | F7: 1991 | G7: Stichting Atlantische Commissie | H7: serial | I7: https://www.jstor.org/journal/atlantischnieuws | J7: atlantischnieuws | K7: Coverage for this title ends with Vol. 49, No. 2 (2025) | M7: =VLOOKUP(B7,[1]Sheet2!A:G, 2, FALSE) -> Regional / Cultural Studies | N7: IITGN | O7: JSTOR | R7: =VLOOKUP(B7,[1]Sheet2!A:G, 4, FALSE) -> 1202 | U7: =VLOOKUP(B7,[1]Sheet2!A:G, 5, FALSE) -> Cultural Studies | V7: =VLOOKUP(B7,[1]Sheet2!A:G, 6, FALSE) -> Arts and Humanities | W7: =VLOOKUP(B7,[1]Sheet2!A:G, 7, FALSE) -> Social Sciences
A8: 14140 | B8: Atlantische Tijdingen | C8: 0067-0235 | D8: 2949-8120 | E8: 1964 | F8: 1978 | G8: Stichting Atlantische Commissie | H8: serial | I8: https://www.jstor.org/journal/atlatijd | J8: atlatijd | K8: Coverage for this title ends with Vol. 49, No. 2 (2025) | M8: =VLOOKUP(B8,[1]Sheet2!A:G, 2, FALSE) -> Regional / Cultural Studies | N8: IITGN | O8: JSTOR | R8: =VLOOKUP(B8,[1]Sheet2!A:G, 4, FALSE) -> 1202 | U8: =VLOOKUP(B8,[1]Sheet2!A:G, 5, FALSE) -> Cultural Studies | V8: =VLOOKUP(B8,[1]Sheet2!A:G, 6, FALSE) -> Arts and Humanities | W8: =VLOOKUP(B8,[1]Sheet2!A:G, 7, FALSE) -> Social Sciences
A9: 14320 | B9: The Browning Newsletter | C9: 0007-2532 | D9: 2767-1895 | E9: 1968 | F9: 1972 | G9: Armstrong Browning Library and Museum, Baylor University | H9: serial | I9: https://www.jstor.org/journal/brownews | J9: brownews | K9: Publication of this title ceased in 2006. | M9: =VLOOKUP(B9,[1]Sheet2!A:G, 2, FALSE) -> Literary Studies (Victorian Literature) | N9: IITGN | O9: JSTOR | R9: =VLOOKUP(B9,[1]Sheet2!A:G, 4, FALSE) -> 1205 | U9: =VLOOKUP(B9,[1]Sheet2!A:G, 5, FALSE) -> Literature and Literary Theory | V9: =VLOOKUP(B9,[1]Sheet2!A:G, 6, FALSE) -> Arts and Humanities | W9: =VLOOKUP(B9,[1]Sheet2!A:G, 7, FALSE) -> Social Sciences
A10: 14376 | B10: Bulletin (Haldane Society of Socialist Lawyers) | C10: 2517-7281 | D10: 2631-8628 | E10: 1971 | F10: 1980 | G10: Pluto Journals | H10: serial | I10: https://www.jstor.org/journal/bullhaldsocisoci | J10: bullhaldsocisoci | K10: Content for this title is released as soon as the latest issues become available to JSTOR. | M10: =VLOOKUP(B10,[1]Sheet2!A:G, 2, FALSE) -> Law / Legal Studies (Socialist perspective) | N10: IITGN | O10: JSTOR | R10: =VLOOKUP(B10,[1]Sheet2!A:G, 4, FALSE) -> 3308 | U10: =VLOOKUP(B10,[1]Sheet2!A:G, 5, FALSE) -> Law | V10: =VLOOKUP(B10,[1]Sheet2!A:G, 6, FALSE) -> Social Sciences | W10: =VLOOKUP(B10,[1]Sheet2!A:G, 7, FALSE) -> Social Sciences
A11: 14513 | B11: BYU Studies | C11: 2837-0031 | D11: 2837-004X | E11: 2023 | F11: 2023 | G11: Brigham Young University | H11: serial | I11: https://www.jstor.org/journal/byustudies | J11: byustudies | K11: Content for this title is released as soon as the latest issues become available to JSTOR. | M11: =VLOOKUP(B11,[1]Sheet2!A:G, 2, FALSE) -> Religious Studies / Humanities | N11: IITGN | O11: JSTOR | R11: =VLOOKUP(B11,[1]Sheet2!A:G, 4, FALSE) -> 1211 | U11: =VLOOKUP(B11,[1]Sheet2!A:G, 5, FALSE) -> Religious Studies | V11: =VLOOKUP(B11,[1]Sheet2!A:G, 6, FALSE) -> Arts and Humanities | W11: =VLOOKUP(B11,[1]Sheet2!A:G, 7, FALSE) -> Social Sciences
A12: 14621 | B12: Charity Organisation Quarterly | C12: 2398-4880 | D12: 2516-1938 | E12: 1922 | F12: 1939 | G12: Oxford University Press | H12: serial | I12: https://www.jstor.org/journal/charorgaquar | J12: charorgaquar | M12: =VLOOKUP(B12,[1]Sheet2!A:G, 2, FALSE) -> Social Work / Social Policy | N12: IITGN | O12: JSTOR | R12: =VLOOKUP(B12,[1]Sheet2!A:G, 4, FALSE) -> 3313 | U12: =VLOOKUP(B12,[1]Sheet2!A:G, 5, FALSE) -> Social Issues | V12: =VLOOKUP(B12,[1]Sheet2!A:G, 6, FALSE) -> Social Sciences | W12: =VLOOKUP(B12,[1]Sheet2!A:G, 7, FALSE) -> Social Sciences
A13: 14668 | B13: Circeto | C13: 0758-363X | D13: 2669-4301 | E13: 1983 | F13: 1984 | G13: Classiques Garnier | H13: serial | I13: https://www.jstor.org/journal/circeto | J13: circeto | K13: Content for this title is released as soon as the latest issues become available to JSTOR. | M13: =VLOOKUP(B13,[1]Sheet2!A:G, 2, FALSE) -> Natural History / Biology (Ornithology) | N13: IITGN | O13: JSTOR | R13: =VLOOKUP(B13,[1]Sheet2!A:G, 4, FALSE) -> 1105 | U13: =VLOOKUP(B13,[1]Sheet2!A:G, 5, FALSE) -> Ecology, Evolution, Behavior and Systematics | V13: =VLOOKUP(B13,[1]Sheet2!A:G, 6, FALSE) -> Agricultural and Biological Sciences | W13: =VLOOKUP(B13,[1]Sheet2!A:G, 7, FALSE) -> Life Sciences
A14: 14722 | B14: Communist Affairs | C14: 0588-8174 | D14: 1878-3392 | E14: 1962 | F14: 1968 | G14: University of California Press | H14: serial | I14: https://www.jstor.org/journal/communistaffairs | J14: communistaffairs | M14: =VLOOKUP(B14,[1]Sheet2!A:G, 2, FALSE) -> Political Science (Communism / Soviet Studies) | N14: IITGN | O14: JSTOR | P14: 5800184430 | Q14: 5800184430 | R14: =VLOOKUP(B14,[1]Sheet2!A:G, 4, FALSE) -> 3320 | U14: =VLOOKUP(B14,[1]Sheet2!A:G, 5, FALSE) -> Political Science and International Relations | V14: =VLOOKUP(B14,[1]Sheet2!A:G, 6, FALSE) -> Social Sciences | W14: =VLOOKUP(B14,[1]Sheet2!A:G, 7, FALSE) -> Social Sciences
A15: 14754 | B15: The Connecticut Common School Journal (1857-1866) | C15: 2159-0133 | D15: 2639-9202 | E15: 1857 | F15: 1857 | G15: SAGE Publications, Inc. | H15: serial | I15: https://www.jstor.org/journal/conncommschoj2 | J15: conncommschoj2 | M15: Education | N15: IITGN | O15: JSTOR | R15: 3304 | U15: Education | V15: Social Sciences | W15: Social Sciences
A16: 14864 | B16: Dante Studies | C16: 2470-4261 | D16: 2470-427X | E16: 2015 | F16: 2020 | G16: The Johns Hopkins University | H16: serial | I16: https://www.jstor.org/journal/dantestudies2 | J16: dantestudies2 | M16: =VLOOKUP(B16,[1]Sheet2!A:G, 2, FALSE) -> Literary Studies (Italian / Medieval) | N16: IITGN | O16: JSTOR | R16: =VLOOKUP(B16,[1]Sheet2!A:G, 4, FALSE) -> 1205 | U16: =VLOOKUP(B16,[1]Sheet2!A:G, 5, FALSE) -> Literature and Literary Theory | V16: =VLOOKUP(B16,[1]Sheet2!A:G, 6, FALSE) -> Arts and Humanities | W16: =VLOOKUP(B16,[1]Sheet2!A:G, 7, FALSE) -> Social Sciences
A17: 14901 | B17: Dickens Studies Newsletter | C17: 0012-2432 | D17: 2767-1119 | E17: 1970 | F17: 1983 | G17: The Johns Hopkins University | H17: serial | I17: https://www.jstor.org/journal/dickstudnews | J17: dickstudnews | M17: =VLOOKUP(B17,[1]Sheet2!A:G, 2, FALSE) -> Literary Studies (Victorian Literature) | N17: IITGN | O17: JSTOR | R17: =VLOOKUP(B17,[1]Sheet2!A:G, 4, FALSE) -> 1205 | U17: =VLOOKUP(B17,[1]Sheet2!A:G, 5, FALSE) -> Literature and Literary Theory | V17: =VLOOKUP(B17,[1]Sheet2!A:G, 6, FALSE) -> Arts and Humanities | W17: =VLOOKUP(B17,[1]Sheet2!A:G, 7, FALSE) -> Social Sciences
A18: 14964 | B18: Economic History | C18: 2754-1096 | D18: 2753-5398 | E18: 1930 | F18: 1940 | G18: Royal Economic Society | H18: serial | I18: https://www.jstor.org/journal/economichistory | J18: economichistory | M18: =VLOOKUP(B18,[1]Sheet2!A:G, 2, FALSE) -> Economic History | N18: IITGN | O18: JSTOR | R18: =VLOOKUP(B18,[1]Sheet2!A:G, 4, FALSE) -> 2002; 1202 | U18: =VLOOKUP(B18,[1]Sheet2!A:G, 5, FALSE) -> Economics and Econometrics; Cultural Studies | V18: =VLOOKUP(B18,[1]Sheet2!A:G, 6, FALSE) -> Economics; Arts and Humanities | W18: =VLOOKUP(B18,[1]Sheet2!A:G, 7, FALSE) -> Social Sciences
A19: 15343 | B19: Haldane Bulletin | C19: 2517-6021 | D19: 2631-8636 | E19: 1980 | F19: 1983 | G19: Pluto Journals | H19: serial | I19: https://www.jstor.org/journal/haldanebulletin | J19: haldanebulletin | K19: Content for this title is released as soon as the latest issues become available to JSTOR. | M19: =VLOOKUP(B19,[1]Sheet2!A:G, 2, FALSE) -> Law / Political Activism | N19: IITGN | O19: JSTOR | R19: =VLOOKUP(B19,[1]Sheet2!A:G, 4, FALSE) -> 3308 | U19: =VLOOKUP(B19,[1]Sheet2!A:G, 5, FALSE) -> Law | V19: =VLOOKUP(B19,[1]Sheet2!A:G, 6, FALSE) -> Social Sciences | W19: =VLOOKUP(B19,[1]Sheet2!A:G, 7, FALSE) -> Social Sciences
A20: 16598 | B20: Medieval People: Social Bonds, Kinship, and Networks | C20: 2690-8182 | D20: 2690-8190 | E20: 2021 | F20: 2023 | G20: Board of Trustees of Western Michigan University through its Medieval Institute Publications | H20: serial | I20: https://www.jstor.org/journal/medievalpeople | J20: medievalpeople | M20: =VLOOKUP(B20,[1]Sheet2!A:G, 2, FALSE) -> Medieval Studies / Social History | N20: IITGN | O20: JSTOR | R20: =VLOOKUP(B20,[1]Sheet2!A:G, 4, FALSE) -> 1202; 3314 | U20: =VLOOKUP(B20,[1]Sheet2!A:G, 5, FALSE) -> Cultural Studies; Anthropology | V20: =VLOOKUP(B20,[1]Sheet2!A:G, 6, FALSE) -> Arts and Humanities; Social Sciences | W20: =VLOOKUP(B20,[1]Sheet2!A:G, 7, FALSE) -> Social Sciences
A21: 16602 | B21: Medieval World: Culture & Conflict | C21: 2949-7566 | D21: 2949-7574 | E21: 2022 | F21: 2022 | G21: Karwansaray BV | H21: serial | I21: https://www.jstor.org/journal/medievalworld | J21: medievalworld | M21: =VLOOKUP(B21,[1]Sheet2!A:G, 2, FALSE) -> Medieval Studies / History | N21: IITGN | O21: JSTOR | R21: =VLOOKUP(B21,[1]Sheet2!A:G, 4, FALSE) -> 1202; 1206 | U21: =VLOOKUP(B21,[1]Sheet2!A:G, 5, FALSE) -> Cultural Studies; Archaeology | V21: =VLOOKUP(B21,[1]Sheet2!A:G, 6, FALSE) -> Arts and Humanities | W21: =VLOOKUP(B21,[1]Sheet2!A:G, 7, FALSE) -> Social Sciences
A22: 16907 | B22: Newsletter of the Section of Real Property, Probate and Trust Law | C22: 2576-4292 | D22: 2578-014X | E22: 1959 | F22: 1966 | G22: American Bar Association | H22: serial | I22: https://www.jstor.org/journal/newssectrealprop | J22: newssectrealprop | M22: =VLOOKUP(B22,[1]Sheet2!A:G, 2, FALSE) -> Law (Property / Trust Law) | N22: IITGN | O22: JSTOR | R22: =VLOOKUP(B22,[1]Sheet2!A:G, 4, FALSE) -> 3308 | U22: =VLOOKUP(B22,[1]Sheet2!A:G, 5, FALSE) -> Law | V22: =VLOOKUP(B22,[1]Sheet2!A:G, 6, FALSE) -> Social Sciences | W22: =VLOOKUP(B22,[1]Sheet2!A:G, 7, FALSE) -> Social Sciences
A23: 17297 | B23: Proceedings of the Business History Conference | C23: 2576-4888 | D23: 2577-9192 | E23: 1973 | F23: 1975 | G23: Cambridge University Press | H23: serial | I23: https://www.jstor.org/journal/procbusihistconf | J23: procbusihistconf | M23: =VLOOKUP(B23,[1]Sheet2!A:G, 2, FALSE) -> Business History | N23: IITGN | O23: JSTOR | R23: =VLOOKUP(B23,[1]Sheet2!A:G, 4, FALSE) -> 1403; 2002 | U23: =VLOOKUP(B23,[1]Sheet2!A:G, 5, FALSE) -> Business and International Management; Economics | V23: =VLOOKUP(B23,[1]Sheet2!A:G, 6, FALSE) -> Business; Economics | W23: =VLOOKUP(B23,[1]Sheet2!A:G, 7, FALSE) -> Social Sciences
A24: 17642 | B24: Revue internationale des études du développement | C24: 2554-3415 | D24: 2554-3555 | E24: 2017 | F24: 2021 | G24: Éditions de la Sorbonne | H24: serial | I24: https://www.jstor.org/journal/revuinteetuddeve | J24: revuinteetuddeve | M24: =VLOOKUP(B24,[1]Sheet2!A:G, 2, FALSE) -> Development Studies | N24: IITGN | O24: JSTOR | R24: =VLOOKUP(B24,[1]Sheet2!A:G, 4, FALSE) -> 3312 | U24: =VLOOKUP(B24,[1]Sheet2!A:G, 5, FALSE) -> Development Studies | V24: =VLOOKUP(B24,[1]Sheet2!A:G, 6, FALSE) -> Social Sciences | W24: =VLOOKUP(B24,[1]Sheet2!A:G, 7, FALSE) -> Social Sciences
A25: 17765 | B25: Scientific American Mind | C25: 1555-2284 | D25: 2331-379X | E25: 2004 | F25: 2021 | G25: Scientific American, Inc. | H25: serial | I25: https://www.jstor.org/journal/scieamermind | J25: scieamermind | M25: =VLOOKUP(B25,[1]Sheet2!A:G, 2, FALSE) -> Psychology / Cognitive Science | N25: IITGN | O25: JSTOR | R25: =VLOOKUP(B25,[1]Sheet2!A:G, 4, FALSE) -> 3200 | U25: =VLOOKUP(B25,[1]Sheet2!A:G, 5, FALSE) -> Psychology (miscellaneous) | V25: =VLOOKUP(B25,[1]Sheet2!A:G, 6, FALSE) -> Psychology | W25: =VLOOKUP(B25,[1]Sheet2!A:G, 7, FALSE) -> Social Sciences
A26: 17851 | B26: The Social Science News Bulletin | C26: 2689-8578 | D26: 2692-1642 | E26: 1948 | F26: 1949 | G26: The Johns Hopkins University | H26: serial | I26: https://www.jstor.org/journal/sociscienewsbull | J26: sociscienewsbull | M26: =VLOOKUP(B26,[1]Sheet2!A:G, 2, FALSE) -> Social Sciences (General) | N26: IITGN | O26: JSTOR | R26: =VLOOKUP(B26,[1]Sheet2!A:G, 4, FALSE) -> 3300 | U26: =VLOOKUP(B26,[1]Sheet2!A:G, 5, FALSE) -> Social Sciences (general) | V26: =VLOOKUP(B26,[1]Sheet2!A:G, 6, FALSE) -> Social Sciences | W26: =VLOOKUP(B26,[1]Sheet2!A:G, 7, FALSE) -> Social Sciences
A27: 17993 | B27: Studies in Comparative Communism | C27: 0039-3592 | D27: 1878-3341 | E27: 1968 | F27: 1992 | G27: University of California Press | H27: serial | I27: https://www.jstor.org/journal/studcompcomm | J27: studcompcomm | M27: =VLOOKUP(B27,[1]Sheet2!A:G, 2, FALSE) -> Political Science | N27: IITGN | O27: JSTOR | P27: 5800174931 | Q27: 5800174931 | R27: =VLOOKUP(B27,[1]Sheet2!A:G, 4, FALSE) -> 3320 | U27: =VLOOKUP(B27,[1]Sheet2!A:G, 5, FALSE) -> Political Science and International Relations | V27: =VLOOKUP(B27,[1]Sheet2!A:G, 6, FALSE) -> Social Sciences | W27: =VLOOKUP(B27,[1]Sheet2!A:G, 7, FALSE) -> Social Sciences
A28: 18036 | B28: Swainsona | C28: 2206-1649 | D28: 2206-1657 | E28: 2017 | F28: 2024 | G28: Board of the Botanic Gardens and State Herbarium, Adelaide, South Australia | H28: serial | I28: https://www.jstor.org/journal/swainsona | J28: swainsona | K28: Content for this title is released as soon as the latest issues become available to JSTOR. | M28: =VLOOKUP(B28,[1]Sheet2!A:G, 2, FALSE) -> Botany / Plant Science | N28: IITGN | O28: JSTOR | R28: =VLOOKUP(B28,[1]Sheet2!A:G, 4, FALSE) -> 1105 | U28: =VLOOKUP(B28,[1]Sheet2!A:G, 5, FALSE) -> Ecology, Evolution, Behavior and Systematics | V28: =VLOOKUP(B28,[1]Sheet2!A:G, 6, FALSE) -> Agricultural and Biological Sciences | W28: =VLOOKUP(B28,[1]Sheet2!A:G, 7, FALSE) -> Life Sciences
A29: 18037 | B29: Swainsona. Supplement | C29: 2209-7635 | D29: 2209-7643 | E29: 2017 | F29: 2017 | G29: Board of the Botanic Gardens and State Herbarium, Adelaide, South Australia | H29: serial | I29: https://www.jstor.org/journal/swaisupp | J29: swaisupp | M29: =VLOOKUP(B29,[1]Sheet2!A:G, 2, FALSE) -> Botany / Plant Science | N29: IITGN | O29: JSTOR | R29: =VLOOKUP(B29,[1]Sheet2!A:G, 4, FALSE) -> 1105 | U29: =VLOOKUP(B29,[1]Sheet2!A:G, 5, FALSE) -> Ecology, Evolution, Behavior and Systematics | V29: =VLOOKUP(B29,[1]Sheet2!A:G, 6, FALSE) -> Agricultural and Biological Sciences | W29: =VLOOKUP(B29,[1]Sheet2!A:G, 7, FALSE) -> Life Sciences
A30: 18290 | B30: Waka Kuaka: The Journal of the Polynesian Society | C30: 2816-1580 | D30: 2816-1599 | E30: 2022 | F30: 2022 | G30: The University of Auckland | H30: serial | I30: https://www.jstor.org/journal/wakakuakjpolysoc | J30: wakakuakjpolysoc | M30: =VLOOKUP(B30,[1]Sheet2!A:G, 2, FALSE) -> Anthropology / Pacific Studies | N30: IITGN | O30: JSTOR | R30: =VLOOKUP(B30,[1]Sheet2!A:G, 4, FALSE) -> 3314; 1202 | U30: =VLOOKUP(B30,[1]Sheet2!A:G, 5, FALSE) -> Anthropology; Cultural Studies | V30: =VLOOKUP(B30,[1]Sheet2!A:G, 6, FALSE) -> Social Sciences; Arts and Humanities | W30: =VLOOKUP(B30,[1]Sheet2!A:G, 7, FALSE) -> Social Sciences
A31: 18437 | B31: Zeitschrift für Gemeinwirtschaft und Gemeinwohl: Z'Gug / Journal of Social Economy and Common Welfare | C31: 2701-4193 | D31: 2701-4207 | E31: 2021 | F31: 2023 | G31: Nomos Verlagsgesellschaft mbH & Co. KG | H31: serial | I31: https://www.jstor.org/journal/zeitgemegemejsoc | J31: zeitgemegemejsoc | M31: Economics; Social Issues | N31: IITGN | O31: JSTOR | R31: 2002; 3313 | U31: Economics; Social Issues | V31: Economics; Social Sciences | W31: Social Sciences
A32: 18472 | B32: Zeitschrift für Theologie und Philosophie | C32: 2709-8427 | D32: 2709-8435 | E32: 2021 | F32: 2022 | G32: Austrian Province of the Society of Jesus | H32: serial | I32: https://www.jstor.org/journal/zeittheophil | J32: zeittheophil | M32: =VLOOKUP(B32,[1]Sheet2!A:G, 2, FALSE) -> Theology / Philosophy | N32: IITGN | O32: JSTOR | R32: =VLOOKUP(B32,[1]Sheet2!A:G, 4, FALSE) -> 1211; 1210 | U32: =VLOOKUP(B32,[1]Sheet2!A:G, 5, FALSE) -> Religious Studies; Philosophy | V32: =VLOOKUP(B32,[1]Sheet2!A:G, 6, FALSE) -> Arts and Humanities | W32: =VLOOKUP(B32,[1]Sheet2!A:G, 7, FALSE) -> Social Sciences

Sheet Sheet9
A1: sr.no. | B1: subjectname | C1: ASJC Code | D1: ASJC Description | E1: Main Subject | F1: Supergroup
A2: 3 | B2: General Computer Science | C2: 1700 | D2: General Computer Science | E2: Computer Science | F2: Physical Sciences
A3: 10 | B3: Software | C3: 1712 | D3: Software | E3: Computer Science | F3: Physical Sciences
A4: 53 | B4: Condensed Matter Physics; Mechanics of Materials; General Materials Science; General Chemistry; Mechanical Engineering | C4: 3104; 2211; 2500; 1600; 2210 | D4: Condensed Matter Physics; Mechanics of Materials; General Materials Science; General Chemistry; Mechanical Engineering | E4: Physics and Astronomy; Engineering; Materials Science; Chemistry | F4: Physical Sciences
A5: 55 | B5: Hardware and Architecture; Computer Networks and Communications | C5: 1708; 1705 | D5: Hardware and Architecture; Computer Networks and Communications | E5: Computer Science | F5: Physical Sciences
A6: 56 | B6: Condensed Matter Physics; Mechanics of Materials; General Materials Science; General Chemistry; Mechanical Engineering | C6: 3104; 2211; 2500; 1600; 2210 | D6: Condensed Matter Physics; Mechanics of Materials; General Materials Science; General Chemistry; Mechanical Engineering | E6: Physics and Astronomy; Engineering; Materials Science; Chemistry | F6: Physical Sciences
A7: 57 | B7: Condensed Matter Physics; Mechanics of Materials; General Materials Science; General Chemistry; Mechanical Engineering | C7: 3104; 2211; 2500; 1600; 2210 | D7: Condensed Matter Physics; Mechanics of Materials; General Materials Science; General Chemistry; Mechanical Engineering | E7: Physics and Astronomy; Engineering; Materials Science; Chemistry | F7: Physical Sciences
A8: 58 | B8: Condensed Matter Physics; Mechanics of Materials; General Materials Science; General Chemistry; Mechanical Engineering | C8: 3104; 2211; 2500; 1600; 2210 | D8: Condensed Matter Physics; Mechanics of Materials; General Materials Science; General Chemistry; Mechanical Engineering | E8: Physics and Astronomy; Engineering; Materials Science; Chemistry | F8: Physical Sciences
A9: 59 | B9: Experimental and Cognitive Psychology | C9: 3205 | D9: Experimental and Cognitive Psychology | E9: Psychology | F9: Social Sciences
A10: 61 | B10: Computer Networks and Communications | C10: 1705 | D10: Computer Networks and Communications | E10: Computer Science | F10: Physical Sciences
A11: 62 | B11: Software | C11: 1712 | D11: Software | E11: Computer Science | F11: Physical Sciences
A12: 65 | B12: General Computer Science; Education | C12: 1700; 3304 | D12: General Computer Science; Education | E12: Computer Science; Social Sciences | F12: Physical Sciences; Social Sciences
A13: 66 | B13: General Engineering | C13: 2200 | D13: General Engineering | E13: Engineering | F13: Physical Sciences
... A405: 4164 | B405: Horticulture | C405: 1108 | D405: Horticulture | E405: Agricultural and Biological Sciences | F405: Life Sciences
A406: 4165 | B406: Medical; Surgical | C406: 2746 | D406: Surgical | E406: Medicine | F406: Health Sciences
A407: 4166 | B407: Plant Science | C407: 1110 | D407: Plant Science | E407: Agricultural and Biological Sciences | F407: Life Sciences
A408: 4167 | B408: General Agricultural and Biological Sciences | C408: 1100 | D408: General Agricultural and Biological Sciences | E408: Agricultural and Biological Sciences | F408: Life Sciences
A409: 4169 | B409: Philosophy | C409: 1211 | D409: Philosophy | E409: Arts and Humanities | F409: Social Sciences
A410: 4170 | B410: General Energy; General Environmental Science | C410: 2100; 2300 | D410: General Energy; General Environmental Science | E410: Energy; Environmental Science | F410: Physical Sciences
A411: 4171 | B411: Water Science and Technology | C411: 2312 | D411: Water Science and Technology | E411: Environmental Science | F411: Physical Sciences
A412: 4173 | B412: Health, Toxicology and Mutagenesis | C412: 2307 | D412: Health, Toxicology and Mutagenesis | E412: Environmental Science | F412: Physical Sciences
A413: 4174 | B413: Forestry | C413: 1107 | D413: Forestry | E413: Agricultural and Biological Sciences | F413: Life Sciences
A414: 4175 | B414: General Veterinary | C414: 3400 | D414: General Veterinary | E414: Veterinary | F414: Health Sciences
A415: 4176 | B415: Geography, Planning and Development | C415: 3305 | D415: Geography, Planning and Development | E415: Social Sciences | F415: Social Sciences
A416: 4177 | B416: Education | C416: 3304 | D416: Education | E416: Social Sciences | F416: Social Sciences
A417: 4179 | B417: Library and Information Sciences | C417: 3309 | D417: Library and Information Sciences | E417: Social Sciences | F417: Social Sciences
A418: 4180 | B418: Cell Biology; Developmental Biology | C418: 1307; 1309 | D418: Cell Biology; Developmental Biology | E418: Biochemistry, Genetics and Molecular Biology | F418: Life Sciences
... A901: 8875 | B901: Transportation; Development; Geography, Planning and Development; General Economics, Econometrics and Finance | C901: 3313; 3303; 3305; 2000 | D901: Transportation; Development; Geography, Planning and Development; General Economics, Econometrics and Finance | E901: Social Sciences; Economics, Econometrics and Finance | F901: Social Sciences
A902: 8904 | B902: Medical; Surgical | C902: 2746 | D902: Surgical | E902: Medicine | F902: Health Sciences
A903: 8909 | B903: Dermatology | C903: 2708 | D903: Dermatology | E903: Medicine | F903: Health Sciences
A904: 8912 | B904: Automotive Engineering; Electrical and Electronic Engineering; Electronic, Optical and Magnetic Materials | C904: 2203; 2208; 2504 | D904: Automotive Engineering; Electrical and Electronic Engineering; Electronic, Optical and Magnetic Materials | E904: Engineering; Materials Science | F904: Physical Sciences
A905: 8914 | B905: Economics, Econometrics and Finance (miscellaneous); Finance; General Economics, Econometrics and Finance | C905: 2001; 2003; 2000 | D905: Economics, Econometrics and Finance (miscellaneous); Finance; General Economics, Econometrics and Finance | E905: Economics, Econometrics and Finance | F905: Social Sciences
A906: 8915 | B906: General Psychology; Psychology (miscellaneous); Sociology and Political Science | C906: 3200; 3201; 3312 | D906: General Psychology; Psychology (miscellaneous); Sociology and Political Science | E906: Psychology; Social Sciences | F906: Social Sciences
A907: 8927 | B907: Cardiology and Cardiovascular Medicine | C907: 2705 | D907: Cardiology and Cardiovascular Medicine | E907: Medicine | F907: Health Sciences
A908: 8935 | B908: Geography, Planning and Development | C908: 3305 | D908: Geography, Planning and Development | E908: Social Sciences | F908: Social Sciences
A909: 8941 | B909: Business, Management and Accounting (miscellaneous) | C909: 1401 | D909: Business, Management and Accounting (miscellaneous) | E909: Business, Management and Accounting | F909: Social Sciences
A910: 8944 | B910: Computer Science (miscellaneous); General Computer Science | C910: 1701; 1700 | D910: Computer Science (miscellaneous); General Computer Science | E910: Computer Science | F910: Physical Sciences
A911: 8957 | B911: Oncology | C911: 2730 | D911: Oncology | E911: Medicine | F911: Health Sciences
A912: 8959 | B912: Gastroenterology | C912: 2715 | D912: Gastroenterology | E912: Medicine | F912: Health Sciences
A913: 8965 | B913: Obstetrics and Gynaecology | C913: 2729 | D913: Obstetrics and Gynecology | E913: Medicine | F913: Health Sciences
A914: 8967 | B914: General Psychology; Psychology (miscellaneous) | C914: 3200; 3201 | D914: General Psychology; Psychology (miscellaneous) | E914: Psychology | F914: Social Sciences
... A917: 8970 | B917: Reviews and References, Medical | C917: 2744 | D917: Reviews and References (medical) | E917: Medicine | F917: Health Sciences
A918: 8971 | B918: Medical; Surgical | C918: 2746 | D918: Surgical | E918: Medicine | F918: Health Sciences
A919: 8975 | B919: General Computer Science | C919: 1700 | D919: General Computer Science | E919: Computer Science | F919: Physical Sciences
A920: 8977 | B920: Otorhinolaryngology | C920: 2733 | D920: Otorhinolaryngology | E920: Medicine | F920: Health Sciences
A921: 8981 | B921: Chemical Engineering (miscellaneous); General Chemical Engineering | C921: 1501; 1500 | D921: Chemical Engineering (miscellaneous); General Chemical Engineering | E921: Chemical Engineering | F921: Physical Sciences
A922: 8983 | B922: Oncology | C922: 2730 | D922: Oncology | E922: Medicine | F922: Health Sciences
A923: 8985 | B923: Endocrinology | C923: 1310 | D923: Endocrinology | E923: Biochemistry, Genetics and Molecular Biology | F923: Life Sciences
A924: 8986 | B924: Neurology; Neuropsychology and Physiological Psychology; Psychiatry and Mental health | C924: 2808; 3206; 2738 | D924: Neurology; Neuropsychology and Physiological Psychology; Psychiatry and Mental health | E924: Neuroscience; Psychology; Medicine | F924: Life Sciences; Social Sciences; Health Sciences
A925: 8987 | B925: Management of Technology and Innovation; Public Administration | C925: 1405; 3321 | D925: Management of Technology and Innovation; Public Administration | E925: Business, Management and Accounting; Social Sciences | F925: Social Sciences
A926: 8992 | B926: Arts and Humanities (miscellaneous) | C926: 1201 | D926: Arts and Humanities (miscellaneous) | E926: Arts and Humanities | F926: Social Sciences
A927: 8998 | B927: Sociology and Political Science | C927: 3312 | D927: Sociology and Political Science | E927: Social Sciences | F927: Social Sciences
A928: 9005 | B928: General Business, Management and Accounting; Business, Management and Accounting (miscellaneous); Computer Science Applications | C928: 1400; 1401; 1706 | D928: General Business, Management and Accounting; Business, Management and Accounting (miscellaneous); Computer Science Applications | E928: Business, Management and Accounting; Computer Science | F928: Social Sciences; Physical Sciences
A929: 9015 | B929: Endocrinology; Obstetrics and Gynaecology | C929: 1310; 2729 | D929: Endocrinology; Obstetrics and Gynecology | E929: Biochemistry, Genetics and Molecular Biology; Medicine | F929: Life Sciences; Health Sciences
A930: 9023 | B930: Biochemistry, Genetics and Molecular Biology (miscellaneous); General Biochemistry, Genetics and Molecular Biology; Medical; Surgical | C930: 1301; 1300 | D930: Biochemistry, Genetics and Molecular Biology (miscellaneous); General Biochemistry, Genetics and Molecular Biology; No match: Medical?Surgical | E930: Biochemistry, Genetics and Molecular Biology | F930: Life Sciences
... A956: 9152 | B956: Economics, Econometrics and Finance (miscellaneous); Finance | C956: 2001; 2003 | D956: Economics, Econometrics and Finance (miscellaneous); Finance | E956: Economics, Econometrics and Finance | F956: Social Sciences
A957: 9156 | B957: Medical; Surgical | C957: 2746 | D957: Surgical | E957: Medicine | F957: Health Sciences
A958: 9158 | B958: General Business, Management and Accounting | C958: 1400 | D958: General Business, Management and Accounting | E958: Business, Management and Accounting | F958: Social Sciences
A959: 9159 | B959: Dentistry (miscellaneous); General Dentistry | C959: 3501; 3500 | D959: Dentistry (miscellaneous); General Dentistry | E959: Dentistry | F959: Health Sciences
A960: 9160 | B960: Industrial relations | C960: 1410 | D960: Industrial relations | E960: Business, Management and Accounting | F960: Social Sciences
A961: 9161 | B961: Education | C961: 3304 | D961: Education | E961: Social Sciences | F961: Social Sciences
A962: 9162 | B962: Education | C962: 3304 | D962: Education | E962: Social Sciences | F962: Social Sciences
A963: 9163 | B963: Philosophy | C963: 1211 | D963: Philosophy | E963: Arts and Humanities | F963: Social Sciences
A964: 9164 | B964: Political Science and International Relations | C964: 3320 | D964: Political Science and International Relations | E964: Social Sciences | F964: Social Sciences
A965: 9166 | B965: Education | C965: 3304 | D965: Education | E965: Social Sciences | F965: Social Sciences
A966: 9169 | B966: Literature and Literary Theory; Political Science and International Relations; Sociology and Political Science | C966: 1208; 3320; 3312 | D966: Literature and Literary Theory; Political Science and International Relations; Sociology and Political Science | E966: Arts and Humanities; Social Sciences | F966: Social Sciences
A967: 9170 | B967: Religious studies | C967: 1212 | D967: Religious studies | E967: Arts and Humanities | F967: Social Sciences
A968: 9173 | B968: Sociology and Political Science | C968: 3312 | D968: Sociology and Political Science | E968: Social Sciences | F968: Social Sciences
A969: 9174 | B969: Gerontology | C969: 2909 | D969: Gerontology | E969: Nursing | F969: Health Sciences
... A2758: 18481 | B2758: Area Studies ; History ; Jewish Studies | C2758: 1202 | D2758: No match: Area Studies; History; No match: Jewish Studies | E2758: Arts and Humanities | F2758: Social Sciences
